arcas/__init__.py
arcas/tools.py
arcas/version.py
arcas/IEEE/__init__.py
arcas/IEEE/main.py
arcas/PLOS/__init__.py
arcas/PLOS/main.py
arcas/Springer/__init__.py
arcas/Springer/api_key.py
arcas/Springer/main.py
arcas/arXiv/__init__.py
arcas/arXiv/main.py
arcas/nature/__init__.py
arcas/nature/main.py
arcas-0.0.1.data/scripts/arcas_scrape
arcas-0.0.1.dist-info/DESCRIPTION.rst
arcas-0.0.1.dist-info/METADATA
arcas-0.0.1.dist-info/RECORD
arcas-0.0.1.dist-info/WHEEL
arcas-0.0.1.dist-info/metadata.json
arcas-0.0.1.dist-info/top_level.txt
