Metadata-Version: 2.0
Name: arcas
Version: 0.0.1
Summary: A library to gather data from academic apis
Home-page: UNKNOWN
Author: Nikoleta Glynatsi
Author-email: glynatsine@cardiff.ac.uk
License: The MIT License (MIT)
Platform: UNKNOWN
Requires-Dist: docopt
Requires-Dist: ratelimit (==1.1.0)
Requires-Dist: requests (==2.12.1)
Requires-Dist: requests-mock (==1.1.0)
